trytond/modules/account_personal/__init__.py
trytond/modules/account_personal/account_personal.xml
trytond/modules/account_personal/tryton.cfg
trytond/modules/account_personal/tests/__init__.py
trytond/modules/account_personal/tests/test_account_personal.py
trytonlq_account_personal-5.6.0.dist-info/DESCRIPTION.rst
trytonlq_account_personal-5.6.0.dist-info/METADATA
trytonlq_account_personal-5.6.0.dist-info/RECORD
trytonlq_account_personal-5.6.0.dist-info/WHEEL
trytonlq_account_personal-5.6.0.dist-info/entry_points.txt
trytonlq_account_personal-5.6.0.dist-info/metadata.json
trytonlq_account_personal-5.6.0.dist-info/top_level.txt
